{
  "version": 4,
  "dmapp": "300",
  "constraints": [
    {
      "constraintId": "anim",
      "personal": {
        "prefSize": {
          "width": 400,
          "height": 140
        },
        "minSize": {
          "width": 400,
          "height": 140
        },
        "aspect": "400:140",
        "priority": 0,
        "audio": true
      },
      "communal": {
        "prefSize": {
          "width": 400,
          "height": 140
        },
        "minSize": {
          "width": 400,
          "height": 140
        },
        "aspect": "400:140",
        "priority": 1,
        "audio": true
      }
    }
  ],
  "layoutModel": "packer"
}